ai/__init__.py
ai/openai.py
utils/__init__.py
utils/request.py
aitools_schuanhe-0.1.dist-info/METADATA
aitools_schuanhe-0.1.dist-info/WHEEL
aitools_schuanhe-0.1.dist-info/top_level.txt
aitools_schuanhe-0.1.dist-info/RECORD
