Metadata-Version: 2.1
Name: aitools-schuanhe
Version: 0.1
Summary: 这是一个方便快捷使用ai的包
Author: schuanhe
Author-email: schuanhe@qq.com
Requires-Dist: requests
